LICENSE
README.md
setup.py
GDBIGtools/GDBIGtools.py
GDBIGtools/GDBIGtools_v1.1.0.py
GDBIGtools/GDBIGtools_v1.1.6.py
GDBIGtools/__init__.py
GDBIGtools.egg-info/PKG-INFO
GDBIGtools.egg-info/SOURCES.txt
GDBIGtools.egg-info/dependency_links.txt
GDBIGtools.egg-info/entry_points.txt
GDBIGtools.egg-info/requires.txt
GDBIGtools.egg-info/top_level.txt