Metadata-Version: 2.1
Name: GDBIGtools
Version: 1.1.6
Summary: GDBIGtools: A command line tools for GDBIG variant browser.
Home-page: https://github.com/aiyacharley/GDBIGtools
Author: Chengrui Wang
Author-email: aiyacharley@outlook.com
Maintainer: Chengrui Wang
Maintainer-email: aiyacharley@outlook.com
License: BSD (3-clause)
Download-URL: https://github.com/aiyacharley/GDBIGtools
Platform: UNKNOWN
Classifier: Intended Audience :: Science/Research
Classifier: Programming Language :: Python :: 3.6
Classifier: Programming Language :: Python :: 3.7
Classifier: Programming Language :: Python :: 3.8
Classifier: Programming Language :: Python :: 3.9
Classifier: License :: OSI Approved :: BSD License
Classifier: Topic :: Scientific/Engineering :: Bio-Informatics
Classifier: Operating System :: POSIX
Classifier: Operating System :: POSIX :: Linux
Classifier: Operating System :: MacOS
License-File: LICENSE
